kommo_sdk_data_engineer/__init__.py
kommo_sdk_data_engineer/config.py
kommo_sdk_data_engineer/kommo.py
kommo_sdk_data_engineer/utils.py
kommo_sdk_data_engineer/endpoints/__init__.py
kommo_sdk_data_engineer/endpoints/companies.py
kommo_sdk_data_engineer/endpoints/contacts.py
kommo_sdk_data_engineer/endpoints/custom_fields.py
kommo_sdk_data_engineer/endpoints/events.py
kommo_sdk_data_engineer/endpoints/leads.py
kommo_sdk_data_engineer/endpoints/pipelines.py
kommo_sdk_data_engineer/endpoints/users.py
kommo_sdk_data_engineer/models/__init__.py
kommo_sdk_data_engineer/models/company_models.py
kommo_sdk_data_engineer/models/contact_models.py
kommo_sdk_data_engineer/models/custom_field_models.py
kommo_sdk_data_engineer/models/event_models.py
kommo_sdk_data_engineer/models/lead_models.py
kommo_sdk_data_engineer/models/pipeline_models.py
kommo_sdk_data_engineer/models/user_models.py
kommo_sdk_data_engineer-0.11.0.dist-info/licenses/LICENSE
kommo_sdk_data_engineer-0.11.0.dist-info/METADATA
kommo_sdk_data_engineer-0.11.0.dist-info/WHEEL
kommo_sdk_data_engineer-0.11.0.dist-info/top_level.txt
kommo_sdk_data_engineer-0.11.0.dist-info/RECORD
