Metadata-Version: 2.4
Name: kommo_sdk_data_engineer
Version: 0.11.0
Summary: kommo SDK for Data Enginner is a comprehensive Python SDK designed for data engineers working with the Kommo API.
Author-email: Mailson Náscin <mailson.nascin@gmail.com>
License: MIT
Project-URL: Homepage, https://github.com/nascin/kommo-sdk-data-engineer
Project-URL: Source Code, https://github.com/nascin/kommo-sdk-data-engineer
Project-URL: Bug Tracker, https://github.com/nascin/kommo-sdk-data-engineer/issues
Keywords: kommo,data engineer
Classifier: Programming Language :: Python :: 3
Classifier: Intended Audience :: Developers
Classifier: License :: OSI Approved :: MIT License
Classifier: Operating System :: OS Independent
Classifier: Topic :: Software Development :: Internationalization
Requires-Python: >=3.12
License-File: LICENSE
Requires-Dist: pandas>=2.1.4
Requires-Dist: requests>=2.32.3
Requires-Dist: pydantic>=2.10.6
Dynamic: license-file
